HashLevenMatch/Kmer.py
HashLevenMatch/Parse.py
HashLevenMatch/__init__.py
HashLevenMatch/matchingProgram.py
HashLevenMatch/matchingScript.py
HashLevenMatch/setup.py
HashLevenMatch-0.1.3.dist-info/LICENSE.txt
HashLevenMatch-0.1.3.dist-info/METADATA
HashLevenMatch-0.1.3.dist-info/WHEEL
HashLevenMatch-0.1.3.dist-info/top_level.txt
HashLevenMatch-0.1.3.dist-info/RECORD
